coinbase_data_fetcher/__init__.py
coinbase_data_fetcher/coins_config.json
coinbase_data_fetcher/config.py
coinbase_data_fetcher/config_loader.py
coinbase_data_fetcher/fetcher.py
coinbase_data_fetcher/models.py
coinbase_data_fetcher/prefetch.py
coinbase_data_fetcher/progress.py
coinbase_data_fetcher/utils.py
coinbase_data_fetcher-0.4.1.dist-info/METADATA
coinbase_data_fetcher-0.4.1.dist-info/WHEEL
coinbase_data_fetcher-0.4.1.dist-info/entry_points.txt
coinbase_data_fetcher-0.4.1.dist-info/top_level.txt
coinbase_data_fetcher-0.4.1.dist-info/RECORD
