Metadata-Version: 2.4
Name: coinbase-data-fetcher
Version: 0.4.1
Summary: A Python library for fetching cryptocurrency data from Coinbase
Author: TradeOptimizer Team
License-Expression: MIT
Requires-Python: >=3.9
Requires-Dist: pandas>=2.0.0
Requires-Dist: numpy>=1.24.0
Requires-Dist: pydantic>=2.0.0
Requires-Dist: requests>=2.31.0
Requires-Dist: ratelimit>=2.2.1
Requires-Dist: tenacity>=8.2.0
Requires-Dist: tqdm>=4.65.0
Requires-Dist: aiohttp>=3.8.0
Provides-Extra: dev
Requires-Dist: pytest>=7.0.0; extra == "dev"
Requires-Dist: pytest-cov>=4.0.0; extra == "dev"
Requires-Dist: ruff>=0.1.0; extra == "dev"
Requires-Dist: pyright>=1.1.0; extra == "dev"
